virt_wrapper/__init__.py
virt_wrapper/base.py
virt_wrapper/disk.py
virt_wrapper/hypervisor.py
virt_wrapper/memory.py
virt_wrapper/network.py
virt_wrapper/snapshot.py
virt_wrapper/storage.py
virt_wrapper/vm.py
virt_wrapper/drivers/hyperv.py
virt_wrapper/drivers/kvm.py
virt_wrapper-0.7.1.dist-info/METADATA
virt_wrapper-0.7.1.dist-info/WHEEL
virt_wrapper-0.7.1.dist-info/top_level.txt
virt_wrapper-0.7.1.dist-info/RECORD
