Metadata-Version: 2.4
Name: virt-wrapper
Version: 0.7.1
Summary: Wrapper that was developed in order to manage libvirt virtual machines
Author-email: Dmitry Fateev <dimkaaaa1@gmail.com>
Project-URL: Homepage, https://gitlab.com/Palit_Invalid/virt-wrapper
Project-URL: Issues, https://gitlab.com/Palit_Invalid/virt-wrapper/-/issues
Requires-Python: >=3.10
Requires-Dist: jinja2>=3.1.6
Requires-Dist: libvirt-python>=11.6.0
Requires-Dist: pywinrm>=0.4.3
